concha/__init__.py
concha/environment.py
concha/importers.py
concha/model.py
concha/planner.py
concha/product.py
concha/weather.py
concha-0.3.5.dist-info/AUTHORS.rst
concha-0.3.5.dist-info/LICENSE.txt
concha-0.3.5.dist-info/METADATA
concha-0.3.5.dist-info/WHEEL
concha-0.3.5.dist-info/top_level.txt
concha-0.3.5.dist-info/RECORD
