Metadata-Version: 2.1
Name: concha
Version: 0.3.5
Summary: Concha finds the optimal amount of perishable goods to produce.
Home-page: https://github.com/Ready4theCrush/concha
Author: Thomas Haley
Author-email: thomashaleyds@gmail.com
License: mit
Project-URL: Documentation, https://github.com/Ready4theCrush/concha/blob/master/notebooks/01_run_a_simulation.ipynb
Platform: any
Classifier: Development Status :: 4 - Beta
Classifier: Programming Language :: Python
Classifier: Topic :: Office/Business :: Financial :: Point-Of-Sale
Requires-Python: >=3.6
Requires-Dist: tensorflow (>=2.2)
Requires-Dist: statsmodels
Requires-Dist: pandas
Requires-Dist: scikit-learn
Requires-Dist: seaborn
Requires-Dist: scipy
Requires-Dist: geocoder
Requires-Dist: squareup
Requires-Dist: pytz
